snitch_stitch/__init__.py
snitch_stitch/backend_scanner.py
snitch_stitch/cli.py
snitch_stitch/diff_display.py
snitch_stitch/fixer.py
snitch_stitch/frontend_scanner.py
snitch_stitch/ingest.py
snitch_stitch/ranker.py
snitch_stitch-0.1.1.dist-info/licenses/LICENSE
snitch_stitch-0.1.1.dist-info/METADATA
snitch_stitch-0.1.1.dist-info/WHEEL
snitch_stitch-0.1.1.dist-info/entry_points.txt
snitch_stitch-0.1.1.dist-info/top_level.txt
snitch_stitch-0.1.1.dist-info/RECORD
