Metadata-Version: 2.4
Name: snitch-stitch
Version: 0.1.1
Summary: A security auditor CLI for Git repositories using LLMs
Author-email: Advait Shinde <your-email@example.com>
License:                                  Apache License
Project-URL: Homepage, https://github.com/adv-11/snitch-stitch
Project-URL: Repository, https://github.com/adv-11/snitch-stitch
Project-URL: Issues, https://github.com/adv-11/snitch-stitch/issues
Classifier: Programming Language :: Python :: 3
Classifier: License :: OSI Approved :: Apache Software License
Classifier: Operating System :: OS Independent
Requires-Python: >=3.9
License-File: LICENSE
Dynamic: license-file
